httpcake/__init__.py
httpcake-1.0.0.dist-info/licenses/LICENSE
httpcake-1.0.0.dist-info/METADATA
httpcake-1.0.0.dist-info/WHEEL
httpcake-1.0.0.dist-info/top_level.txt
httpcake-1.0.0.dist-info/RECORD
