Metadata-Version: 2.4
Name: httpcake
Version: 1.0.0
Summary: Library for receiving/sending requests to a site with some anonymization
Home-page: https://LibCake.t.me
Author: FMZNkdv
Author-email: telegram@FMZNkdv.com
License: MIT
License-File: LICENSE
Dynamic: author
Dynamic: author-email
Dynamic: home-page
Dynamic: license
Dynamic: license-file
Dynamic: summary
